ldai_langchain/__init__.py
ldai_langchain/langchain_provider.py
launchdarkly_server_sdk_ai_langchain-0.2.0.dist-info/METADATA
launchdarkly_server_sdk_ai_langchain-0.2.0.dist-info/WHEEL
launchdarkly_server_sdk_ai_langchain-0.2.0.dist-info/RECORD
