Metadata-Version: 2.4
Name: launchdarkly-server-sdk-ai-langchain
Version: 0.2.0
Summary: LaunchDarkly AI SDK LangChain Provider
License: Apache-2.0
Author: LaunchDarkly
Author-email: dev@launchdarkly.com
Requires-Python: >=3.9,<4
Classifier: Intended Audience :: Developers
Classifier: License :: OSI Approved :: Apache Software License
Classifier: Operating System :: OS Independent
Classifier: Programming Language :: Python :: 3
Classifier: Programming Language :: Python :: 3.9
Classifier: Programming Language :: Python :: 3.10
Classifier: Programming Language :: Python :: 3.11
Classifier: Programming Language :: Python :: 3.12
Classifier: Programming Language :: Python :: 3.13
Classifier: Programming Language :: Python :: 3.14
Classifier: Topic :: Software Development
Classifier: Topic :: Software Development :: Libraries
Requires-Dist: langchain (>=0.2.0)
Requires-Dist: langchain-core (>=0.2.0)
Requires-Dist: launchdarkly-server-sdk-ai (>=0.11.0)
Project-URL: Homepage, https://docs.launchdarkly.com/sdk/ai/python
Project-URL: Repository, https://github.com/launchdarkly/python-server-sdk-ai
